fusionflow/upload/__init__.py
fusionflow/upload/base.py
fusionflow/upload/cli.py
fusionflow/upload/fields.py
fusionflow/upload/parameter.py
fusionflow/upload/parse_src.py
fusionflow/upload/sql.py
fusionflow/upload/table.py
fusionflow/upload/utils.py
fusionflow/upload/version.py
fusionflow/upload/db/__init__.py
fusionflow/upload/db/oracle.py
fusionflow/upload/network/__init__.py
fusionflow_upload-0.1.5.dist-info/METADATA
fusionflow_upload-0.1.5.dist-info/WHEEL
fusionflow_upload-0.1.5.dist-info/top_level.txt
fusionflow_upload-0.1.5.dist-info/RECORD
